Workbook
Name Acumulo: Planilha1!$D$18
Name Dividendos_mensais: Planilha1!$D$19
Name Investir_mensal: Planilha1!$D$15
Name Qtd_anos: Planilha1!$D$16
Name Rendimento_Carteira: Planilha1!$D$11
Name Sugestao_Investimento: Planilha1!$D$12
Name Taxa_mensal: Planilha1!$D$17

Sheet Planilha3
A3: Soma de Porcentual Sugerido | B3: Rótulos de Coluna
A4: Rótulos de Linha | B4: 25 | C4: Total Geral
A5: FOFs | B5: 0.05 | C5: 0.05
A6: Total Geral | B6: 0.05 | C6: 0.05

Sheet Planilha1
B9: CONFIGURAÇÕES
B10: Salario | D10: 5000
B11: Rendimento Carteira | D11: 0.01
B12: Sugestão de Investimento | D12: =D10*30% -> 1500
B14: INVESTIMENTO MENSAL
B15: Quando investir por mês? | D15: 500
B16: Por quantos Anos? | D16: 5
B17: Taxa de Rendimento Mensal/ | D17: 0.01079
B18: Patrimônio acumulado? | D18: =FV(Taxa_mensal,Qtd_anos*12,Investir_mensal*-1) -> 41888.457
B19: Dividendos Mensais? | D19: =Acumulo*Rendimento_Carteira -> 418.88457
B21: Cenários | D21: DIVIDENDO
A22: 2 | B22: Quanto em 2 Anos? | C22: =FV($D$17,$A22*12,$D$15*-1) -> 13613.814 | D22: =C22*Rendimento_Carteira -> 136.13814
A23: 5 | B23: Quanto em 5 Anos? | C23: =FV($D$17,$A23*12,$D$15*-1) -> 41888.457 | D23: =C23*Rendimento_Carteira -> 418.88457
A24: 10 | B24: Quanto em 10 Anos? | C24: =FV($D$17,$A24*12,$D$15*-1) -> 121642.11 | D24: =C24*Rendimento_Carteira -> 1216.4211
A25: 20 | B25: Quanto em 20 Anos? | C25: =FV($D$17,$A25*12,$D$15*-1) -> 562599.2 | D25: =C25*Rendimento_Carteira -> 5625.992
A26: 30 | B26: Quanto em 30 Anos? | C26: =FV($D$17,$A26*12,$D$15*-1) -> 2161084.8 | D26: =C26*Rendimento_Carteira -> 21610.848
B30: Perfil | C30: Agressivo
B31: Valor a ser investido por mês | C31: 500
B33: Tipo de FII | C33: Porcentual Sugerido | D33: Valores
B34: PAPEL | C34: =VLOOKUP($C$30&"-"&B34,Planilha2!$A:$D,4,FALSE) -> 0.5 | D34: =C34*$C$31 -> 250
B35: TIJOLO | C35: =VLOOKUP($C$30&"-"&B35,Planilha2!$A:$D,4,FALSE) -> 0.1 | D35: =C35*$C$31 -> 50
B36: HÍBRIDOS | C36: =VLOOKUP($C$30&"-"&B36,Planilha2!$A:$D,4,FALSE) -> 0.05 | D36: =C36*$C$31 -> 25
B37: FOFs | C37: =VLOOKUP($C$30&"-"&B37,Planilha2!$A:$D,4,FALSE) -> 0.05 | D37: =C37*$C$31 -> 25
B38: DESENVOLVIMENTO | C38: =VLOOKUP($C$30&"-"&B38,Planilha2!$A:$D,4,FALSE) -> 0.2 | D38: =C38*$C$31 -> 100
B39: HOTELARIAS | C39: =VLOOKUP($C$30&"-"&B39,Planilha2!$A:$D,4,FALSE) -> 0.1 | D39: =C39*$C$31 -> 50
D40: =SUM(D34:D39) -> 500

Sheet Planilha2
A1: Chave | B1: Perfil | C1: Tipo de FII | D1: %
A2: =B2&"-"&C2 -> Conservador-PAPEL | B2: Conservador | C2: PAPEL | D2: 0.3
A3: =B3&"-"&C3 -> Conservador-TIJOLO | B3: Conservador | C3: TIJOLO | D3: 0.5
A4: =B4&"-"&C4 -> Conservador-HÍBRIDOS | B4: Conservador | C4: HÍBRIDOS | D4: 0.1
A5: =B5&"-"&C5 -> Conservador-FOFs | B5: Conservador | C5: FOFs | D5: 0.1
A6: =B6&"-"&C6 -> Conservador-DESENVOLVIMENTO | B6: Conservador | C6: DESENVOLVIMENTO | D6: 0
A7: =B7&"-"&C7 -> Conservador-HOTELARIAS | B7: Conservador | C7: HOTELARIAS | D7: 0
A8: =B8&"-"&C8 -> Moderado-PAPEL | B8: Moderado | C8: PAPEL | D8: 0.32
A9: =B9&"-"&C9 -> Moderado-TIJOLO | B9: Moderado | C9: TIJOLO | D9: 0.35
A10: =B10&"-"&C10 -> Moderado-HÍBRIDOS | B10: Moderado | C10: HÍBRIDOS | D10: 0.08
A11: =B11&"-"&C11 -> Moderado-FOFs | B11: Moderado | C11: FOFs | D11: 0.05
A12: =B12&"-"&C12 -> Moderado-DESENVOLVIMENTO | B12: Moderado | C12: DESENVOLVIMENTO | D12: 0.1
A13: =B13&"-"&C13 -> Moderado-HOTELARIAS | B13: Moderado | C13: HOTELARIAS | D13: 0.1
... A19: =B19&"-"&C19 -> Agressivo-HOTELARIAS | B19: Agressivo | C19: HOTELARIAS | D19: 0.1
